odoo9_addon_project_double_alias-9.0.1.0.0.99.dev14-py2.7-nspkg.pth
odoo9_addon_project_double_alias-9.0.1.0.0.99.dev14.dist-info/DESCRIPTION.rst
odoo9_addon_project_double_alias-9.0.1.0.0.99.dev14.dist-info/METADATA
odoo9_addon_project_double_alias-9.0.1.0.0.99.dev14.dist-info/RECORD
odoo9_addon_project_double_alias-9.0.1.0.0.99.dev14.dist-info/WHEEL
odoo9_addon_project_double_alias-9.0.1.0.0.99.dev14.dist-info/metadata.json
odoo9_addon_project_double_alias-9.0.1.0.0.99.dev14.dist-info/namespace_packages.txt
odoo9_addon_project_double_alias-9.0.1.0.0.99.dev14.dist-info/top_level.txt
odoo_addons/project_double_alias/README.rst
odoo_addons/project_double_alias/__init__.py
odoo_addons/project_double_alias/__openerp__.py
odoo_addons/project_double_alias/hooks.py
odoo_addons/project_double_alias/i18n/de.po
odoo_addons/project_double_alias/i18n/es.po
odoo_addons/project_double_alias/i18n/es_MX.po
odoo_addons/project_double_alias/i18n/fi.po
odoo_addons/project_double_alias/i18n/fr.po
odoo_addons/project_double_alias/i18n/hr.po
odoo_addons/project_double_alias/i18n/project_double_alias.pot
odoo_addons/project_double_alias/i18n/pt.po
odoo_addons/project_double_alias/i18n/pt_BR.po
odoo_addons/project_double_alias/i18n/pt_PT.po
odoo_addons/project_double_alias/i18n/sl.po
odoo_addons/project_double_alias/i18n/zh_CN.po
odoo_addons/project_double_alias/models/__init__.py
odoo_addons/project_double_alias/models/project_project.py
odoo_addons/project_double_alias/static/description/icon.png
odoo_addons/project_double_alias/static/description/icon.svg
odoo_addons/project_double_alias/tests/__init__.py
odoo_addons/project_double_alias/tests/test_project_double_alias.py
odoo_addons/project_double_alias/views/project_project_view.xml
